flatpak_cargo_generator/__init__.py
flatpak_cargo_generator/script.py
flatpak_cargo_generator-0.1.2.dist-info/LICENSE.md
flatpak_cargo_generator-0.1.2.dist-info/METADATA
flatpak_cargo_generator-0.1.2.dist-info/WHEEL
flatpak_cargo_generator-0.1.2.dist-info/entry_points.txt
flatpak_cargo_generator-0.1.2.dist-info/RECORD
